crontabula/__init__.py
crontabula/__main__.py
crontabula/cli.py
crontabula/py.typed
crontabula-0.1.8.dist-info/METADATA
crontabula-0.1.8.dist-info/WHEEL
crontabula-0.1.8.dist-info/entry_points.txt
crontabula-0.1.8.dist-info/RECORD
