Metadata-Version: 2.3
Name: crontabula
Version: 0.1.8
Summary: Parse crontab expressions with Python
License: MIT
Author: Tom Forbes
Author-email: tom@tomforb.es
Requires-Python: >=3.8,<4.0
Classifier: License :: OSI Approved :: MIT License
Classifier: Programming Language :: Python :: 3
Classifier: Programming Language :: Python :: 3.8
Classifier: Programming Language :: Python :: 3.9
Classifier: Programming Language :: Python :: 3.10
Classifier: Programming Language :: Python :: 3.11
Classifier: Programming Language :: Python :: 3.12
Classifier: Programming Language :: Python :: 3.13
Provides-Extra: cli
Requires-Dist: click ; extra == "cli"
Project-URL: Repository, https://github.com/orf/crontabula
